{
  "type": "proximavis:cindel",
  "generator": {
    "type": "minecraft:noise",
    "settings": "proximavis:cindel",
    "biome_source": {
      "type": "minecraft:multi_noise",
      "biomes": [
        {
          "biome": "proximavis:cindel/volcanic_crater",
          "parameters": {
            "temperature": [
              -1,
              1
            ],
            "humidity": [
              -1,
              1
            ],
            "continentalness": [
              1.9,
              2
            ],
            "erosion": [
              -1,
              1
            ],
            "weirdness": [
              -1,
              1
            ],
            "depth": 0,
            "offset": 0
          }
        },
        {
          "biome": "proximavis:cindel/volcanic_rim",
          "parameters": {
            "temperature": [
              -1,
              1
            ],
            "humidity": [
              -1,
              1
            ],
            "continentalness": [
              0.9,
              1.9
            ],
            "erosion": [
              -1,
              1
            ],
            "weirdness": [
              -1,
              1
            ],
            "depth": 0,
            "offset": 0
          }
        },
        {
          "biome": "proximavis:cindel/volcanic_wastes",
          "parameters": {
            "temperature": [
              -1,
              1
            ],
            "humidity": [
              -1,
              1
            ],
            "continentalness": [
              0.7,
              0.9
            ],
            "erosion": [
              -1,
              1
            ],
            "weirdness": [
              -1,
              1
            ],
            "depth": 0,
            "offset": 0
          }
        },
        {
          "biome": "proximavis:cindel/volcanic_wastes",
          "parameters": {
            "temperature": [
              -1,
              1
            ],
            "humidity": [
              -1,
              -0.25
            ],
            "continentalness": [
              0.5,
              0.7
            ],
            "erosion": [
              -1,
              1
            ],
            "weirdness": [
              -1,
              1
            ],
            "depth": 0,
            "offset": 0
          }
        },
        {
          "biome": "proximavis:cindel/volcanic_valley",
          "parameters": {
            "temperature": [
              -1,
              1
            ],
            "humidity": [
              -0.25,
              1
            ],
            "continentalness": [
              0.5,
              0.7
            ],
            "erosion": [
              -1,
              1
            ],
            "weirdness": [
              -1,
              1
            ],
            "depth": 0,
            "offset": 0
          }
        },
        {
          "biome": "proximavis:cindel/volcanic_valley",
          "parameters": {
            "temperature": [
              -1,
              1
            ],
            "humidity": [
              -1,
              0
            ],
            "continentalness": [
              0.1,
              0.5
            ],
            "erosion": [
              -1,
              1
            ],
            "weirdness": [
              -1,
              1
            ],
            "depth": 0,
            "offset": 0
          }
        },
        {
          "biome": "proximavis:cindel/permian_steppe",
          "parameters": {
            "temperature": [
              -1,
              1
            ],
            "humidity": [
              0,
              1
            ],
            "continentalness": [
              0.1,
              0.5
            ],
            "erosion": [
              -1,
              1
            ],
            "weirdness": [
              -1,
              1
            ],
            "depth": 0,
            "offset": 0
          }
        },
        {
          "biome": "proximavis:cindel/cretaceous_copse",
          "parameters": {
            "temperature": [
              -1.0,
              1.0
            ],
            "humidity": [
              -1.0,
              1.0
            ],
            "continentalness": 0.0,
            "erosion": [
              -1.0,
              -0.78
            ],
            "depth": 0.0,
            "weirdness": [
              0.933,
              1.0
            ],
            "offset": 0.0
          }
        },
        {
          "biome": "proximavis:cindel/cretaceous_copse",
          "parameters": {
            "temperature": [
              -1.0,
              1.0
            ],
            "humidity": [
              -1.0,
              1.0
            ],
            "continentalness": 0.0,
            "erosion": [
              -0.78,
              -0.375
            ],
            "depth": 0.0,
            "weirdness": [
              0.933,
              1.0
            ],
            "offset": 0.0
          }
        },
        {
          "biome": "proximavis:cindel/cretaceous_copse",
          "parameters": {
            "temperature": [
              -1.0,
              1.0
            ],
            "humidity": [
              -1.0,
              1.0
            ],
            "continentalness": 0.0,
            "erosion": [
              -0.375,
              -0.223
            ],
            "depth": 0.0,
            "weirdness": [
              0.933,
              1.0
            ],
            "offset": 0.0
          }
        },
        {
          "biome": "proximavis:cindel/cretaceous_copse",
          "parameters": {
            "temperature": [
              -1.0,
              1.0
            ],
            "humidity": [
              -1.0,
              1.0
            ],
            "continentalness": 0.0,
            "erosion": [
              -0.223,
              0.05
            ],
            "depth": 0.0,
            "weirdness": [
              0.933,
              1.0
            ],
            "offset": 0.0
          }
        },
        {
          "biome": "proximavis:cindel/cretaceous_copse",
          "parameters": {
            "temperature": [
              -1.0,
              1.0
            ],
            "humidity": [
              -1.0,
              1.0
            ],
            "continentalness": 0.0,
            "erosion": [
              0.05,
              0.45
            ],
            "depth": 0.0,
            "weirdness": [
              0.933,
              1.0
            ],
            "offset": 0.0
          }
        },
        {
          "biome": "proximavis:cindel/cretaceous_copse",
          "parameters": {
            "temperature": [
              -1.0,
              1.0
            ],
            "humidity": [
              -1.0,
              1.0
            ],
            "continentalness": 0.0,
            "erosion": [
              0.45,
              0.55
            ],
            "depth": 0.0,
            "weirdness": [
              0.933,
              1.0
            ],
            "offset": 0.0
          }
        },
        {
          "biome": "proximavis:cindel/carboniferous_swamp",
          "parameters": {
            "temperature": [
              -1.0,
              1.0
            ],
            "humidity": [
              -1.0,
              1.0
            ],
            "continentalness": 0.0,
            "erosion": [
              0.55,
              1.0
            ],
            "depth": 0.0,
            "weirdness": [
              0.933,
              1.0
            ],
            "offset": 0.0
          }
        },
        {
          "biome": "proximavis:cindel/cretaceous_copse",
          "parameters": {
            "temperature": [
              -1.0,
              1.0
            ],
            "humidity": [
              -1.0,
              1.0
            ],
            "continentalness": 0.0,
            "erosion": [
              -1.0,
              -0.78
            ],
            "depth": 0.0,
            "weirdness": [
              0.767,
              0.933
            ],
            "offset": 0.0
          }
        },
        {
          "biome": "proximavis:cindel/cretaceous_copse",
          "parameters": {
            "temperature": [
              -1.0,
              1.0
            ],
            "humidity": [
              -1.0,
              1.0
            ],
            "continentalness": 0.0,
            "erosion": [
              -0.78,
              -0.375
            ],
            "depth": 0.0,
            "weirdness": [
              0.767,
              0.933
            ],
            "offset": 0.0
          }
        },
        {
          "biome": "proximavis:cindel/cretaceous_copse",
          "parameters": {
            "temperature": [
              -1.0,
              1.0
            ],
            "humidity": [
              -1.0,
              1.0
            ],
            "continentalness": 0.0,
            "erosion": [
              -0.375,
              -0.223
            ],
            "depth": 0.0,
            "weirdness": [
              0.767,
              0.933
            ],
            "offset": 0.0
          }
        },
        {
          "biome": "proximavis:cindel/cretaceous_copse",
          "parameters": {
            "temperature": [
              -1.0,
              1.0
            ],
            "humidity": [
              -1.0,
              1.0
            ],
            "continentalness": 0.0,
            "erosion": [
              -0.223,
              0.05
            ],
            "depth": 0.0,
            "weirdness": [
              0.767,
              0.933
            ],
            "offset": 0.0
          }
        },
        {
          "biome": "proximavis:cindel/cretaceous_copse",
          "parameters": {
            "temperature": [
              -1.0,
              1.0
            ],
            "humidity": [
              -1.0,
              1.0
            ],
            "continentalness": 0.0,
            "erosion": [
              0.05,
              0.45
            ],
            "depth": 0.0,
            "weirdness": [
              0.767,
              0.933
            ],
            "offset": 0.0
          }
        },
        {
          "biome": "proximavis:cindel/cretaceous_copse",
          "parameters": {
            "temperature": [
              -1.0,
              1.0
            ],
            "humidity": [
              -1.0,
              1.0
            ],
            "continentalness": 0.0,
            "erosion": [
              0.45,
              0.55
            ],
            "depth": 0.0,
            "weirdness": [
              0.767,
              0.933
            ],
            "offset": 0.0
          }
        },
        {
          "biome": "proximavis:cindel/jurassic_fields",
          "parameters": {
            "temperature": [
              -1.0,
              1.0
            ],
            "humidity": [
              -1.0,
              1.0
            ],
            "continentalness": 0.0,
            "erosion": [
              0.55,
              1.0
            ],
            "depth": 0.0,
            "weirdness": [
              0.767,
              0.933
            ],
            "offset": 0.0
          }
        },
        {
          "biome": "proximavis:cindel/cretaceous_copse",
          "parameters": {
            "temperature": [
              -1.0,
              1.0
            ],
            "humidity": [
              -1.0,
              1.0
            ],
            "continentalness": 0.0,
            "erosion": [
              -1.0,
              -0.78
            ],
            "depth": 0.0,
            "weirdness": [
              0.567,
              0.767
            ],
            "offset": 0.0
          }
        },
        {
          "biome": "proximavis:cindel/cretaceous_copse",
          "parameters": {
            "temperature": [
              -1.0,
              1.0
            ],
            "humidity": [
              -1.0,
              1.0
            ],
            "continentalness": 0.0,
            "erosion": [
              -0.78,
              -0.375
            ],
            "depth": 0.0,
            "weirdness": [
              0.567,
              0.767
            ],
            "offset": 0.0
          }
        },
        {
          "biome": "proximavis:cindel/cretaceous_copse",
          "parameters": {
            "temperature": [
              -1.0,
              1.0
            ],
            "humidity": [
              -1.0,
              1.0
            ],
            "continentalness": 0.0,
            "erosion": [
              -0.375,
              -0.223
            ],
            "depth": 0.0,
            "weirdness": [
              0.567,
              0.767
            ],
            "offset": 0.0
          }
        },
        {
          "biome": "proximavis:cindel/cretaceous_copse",
          "parameters": {
            "temperature": [
              -1.0,
              1.0
            ],
            "humidity": [
              -1.0,
              1.0
            ],
            "continentalness": 0.0,
            "erosion": [
              -0.223,
              0.05
            ],
            "depth": 0.0,
            "weirdness": [
              0.567,
              0.767
            ],
            "offset": 0.0
          }
        },
        {
          "biome": "proximavis:cindel/cretaceous_copse",
          "parameters": {
            "temperature": [
              -1.0,
              1.0
            ],
            "humidity": [
              -1.0,
              1.0
            ],
            "continentalness": 0.0,
            "erosion": [
              0.05,
              0.45
            ],
            "depth": 0.0,
            "weirdness": [
              0.567,
              0.767
            ],
            "offset": 0.0
          }
        },
        {
          "biome": "proximavis:cindel/cretaceous_copse",
          "parameters": {
            "temperature": [
              -1.0,
              1.0
            ],
            "humidity": [
              -1.0,
              1.0
            ],
            "continentalness": 0.0,
            "erosion": [
              0.45,
              0.55
            ],
            "depth": 0.0,
            "weirdness": [
              0.567,
              0.767
            ],
            "offset": 0.0
          }
        },
        {
          "biome": "proximavis:cindel/jurassic_fields",
          "parameters": {
            "temperature": [
              -1.0,
              1.0
            ],
            "humidity": [
              -1.0,
              1.0
            ],
            "continentalness": 0.0,
            "erosion": [
              0.55,
              1.0
            ],
            "depth": 0.0,
            "weirdness": [
              0.567,
              0.767
            ],
            "offset": 0.0
          }
        },
        {
          "biome": "proximavis:cindel/triassic_thicket",
          "parameters": {
            "temperature": [
              -1.0,
              1.0
            ],
            "humidity": [
              -1.0,
              1.0
            ],
            "continentalness": 0.0,
            "erosion": [
              -1.0,
              -0.78
            ],
            "depth": 0.0,
            "weirdness": [
              0.4,
              0.567
            ],
            "offset": 0.0
          }
        },
        {
          "biome": "proximavis:cindel/triassic_thicket",
          "parameters": {
            "temperature": [
              -1.0,
              1.0
            ],
            "humidity": [
              -1.0,
              1.0
            ],
            "continentalness": 0.0,
            "erosion": [
              -0.78,
              -0.375
            ],
            "depth": 0.0,
            "weirdness": [
              0.4,
              0.567
            ],
            "offset": 0.0
          }
        },
        {
          "biome": "proximavis:cindel/triassic_thicket",
          "parameters": {
            "temperature": [
              -1.0,
              1.0
            ],
            "humidity": [
              -1.0,
              1.0
            ],
            "continentalness": 0.0,
            "erosion": [
              -0.375,
              -0.223
            ],
            "depth": 0.0,
            "weirdness": [
              0.4,
              0.567
            ],
            "offset": 0.0
          }
        },
        {
          "biome": "proximavis:cindel/triassic_thicket",
          "parameters": {
            "temperature": [
              -1.0,
              1.0
            ],
            "humidity": [
              -1.0,
              1.0
            ],
            "continentalness": 0.0,
            "erosion": [
              -0.223,
              0.05
            ],
            "depth": 0.0,
            "weirdness": [
              0.4,
              0.567
            ],
            "offset": 0.0
          }
        },
        {
          "biome": "proximavis:cindel/triassic_thicket",
          "parameters": {
            "temperature": [
              -1.0,
              1.0
            ],
            "humidity": [
              -1.0,
              1.0
            ],
            "continentalness": 0.0,
            "erosion": [
              0.05,
              0.45
            ],
            "depth": 0.0,
            "weirdness": [
              0.4,
              0.567
            ],
            "offset": 0.0
          }
        },
        {
          "biome": "proximavis:cindel/triassic_thicket",
          "parameters": {
            "temperature": [
              -1.0,
              1.0
            ],
            "humidity": [
              -1.0,
              1.0
            ],
            "continentalness": 0.0,
            "erosion": [
              0.45,
              0.55
            ],
            "depth": 0.0,
            "weirdness": [
              0.4,
              0.567
            ],
            "offset": 0.0
          }
        },
        {
          "biome": "proximavis:cindel/jurassic_fields",
          "parameters": {
            "temperature": [
              -1.0,
              1.0
            ],
            "humidity": [
              -1.0,
              1.0
            ],
            "continentalness": 0.0,
            "erosion": [
              0.55,
              1.0
            ],
            "depth": 0.0,
            "weirdness": [
              0.4,
              0.567
            ],
            "offset": 0.0
          }
        },
        {
          "biome": "proximavis:cindel/triassic_thicket",
          "parameters": {
            "temperature": [
              -1.0,
              1.0
            ],
            "humidity": [
              -1.0,
              1.0
            ],
            "continentalness": 0.0,
            "erosion": [
              -1.0,
              -0.78
            ],
            "depth": 0.0,
            "weirdness": [
              0.267,
              0.4
            ],
            "offset": 0.0
          }
        },
        {
          "biome": "proximavis:cindel/triassic_thicket",
          "parameters": {
            "temperature": [
              -1.0,
              1.0
            ],
            "humidity": [
              -1.0,
              1.0
            ],
            "continentalness": 0.0,
            "erosion": [
              -0.78,
              -0.375
            ],
            "depth": 0.0,
            "weirdness": [
              0.267,
              0.4
            ],
            "offset": 0.0
          }
        },
        {
          "biome": "proximavis:cindel/triassic_thicket",
          "parameters": {
            "temperature": [
              -1.0,
              1.0
            ],
            "humidity": [
              -1.0,
              1.0
            ],
            "continentalness": 0.0,
            "erosion": [
              -0.375,
              -0.223
            ],
            "depth": 0.0,
            "weirdness": [
              0.267,
              0.4
            ],
            "offset": 0.0
          }
        },
        {
          "biome": "proximavis:cindel/triassic_thicket",
          "parameters": {
            "temperature": [
              -1.0,
              1.0
            ],
            "humidity": [
              -1.0,
              1.0
            ],
            "continentalness": 0.0,
            "erosion": [
              -0.223,
              0.05
            ],
            "depth": 0.0,
            "weirdness": [
              0.267,
              0.4
            ],
            "offset": 0.0
          }
        },
        {
          "biome": "proximavis:cindel/triassic_thicket",
          "parameters": {
            "temperature": [
              -1.0,
              1.0
            ],
            "humidity": [
              -1.0,
              1.0
            ],
            "continentalness": 0.0,
            "erosion": [
              0.05,
              0.45
            ],
            "depth": 0.0,
            "weirdness": [
              0.267,
              0.4
            ],
            "offset": 0.0
          }
        },
        {
          "biome": "proximavis:cindel/triassic_thicket",
          "parameters": {
            "temperature": [
              -1.0,
              1.0
            ],
            "humidity": [
              -1.0,
              1.0
            ],
            "continentalness": 0.0,
            "erosion": [
              0.45,
              0.55
            ],
            "depth": 0.0,
            "weirdness": [
              0.267,
              0.4
            ],
            "offset": 0.0
          }
        },
        {
          "biome": "proximavis:cindel/carboniferous_swamp",
          "parameters": {
            "temperature": [
              -1.0,
              1.0
            ],
            "humidity": [
              -1.0,
              1.0
            ],
            "continentalness": 0.0,
            "erosion": [
              0.55,
              1.0
            ],
            "depth": 0.0,
            "weirdness": [
              0.267,
              0.4
            ],
            "offset": 0.0
          }
        },
        {
          "biome": "proximavis:cindel/jurassic_fields",
          "parameters": {
            "temperature": [
              -1.0,
              1.0
            ],
            "humidity": [
              -1.0,
              1.0
            ],
            "continentalness": 0.0,
            "erosion": [
              -1.0,
              -0.78
            ],
            "depth": 0.0,
            "weirdness": [
              0.05,
              0.267
            ],
            "offset": 0.0
          }
        },
        {
          "biome": "proximavis:cindel/jurassic_fields",
          "parameters": {
            "temperature": [
              -1.0,
              1.0
            ],
            "humidity": [
              -1.0,
              1.0
            ],
            "continentalness": 0.0,
            "erosion": [
              -0.78,
              -0.375
            ],
            "depth": 0.0,
            "weirdness": [
              0.05,
              0.267
            ],
            "offset": 0.0
          }
        },
        {
          "biome": "proximavis:cindel/jurassic_fields",
          "parameters": {
            "temperature": [
              -1.0,
              1.0
            ],
            "humidity": [
              -1.0,
              1.0
            ],
            "continentalness": 0.0,
            "erosion": [
              -0.375,
              -0.223
            ],
            "depth": 0.0,
            "weirdness": [
              0.05,
              0.267
            ],
            "offset": 0.0
          }
        },
        {
          "biome": "proximavis:cindel/jurassic_fields",
          "parameters": {
            "temperature": [
              -1.0,
              1.0
            ],
            "humidity": [
              -1.0,
              1.0
            ],
            "continentalness": 0.0,
            "erosion": [
              -0.223,
              0.05
            ],
            "depth": 0.0,
            "weirdness": [
              0.05,
              0.267
            ],
            "offset": 0.0
          }
        },
        {
          "biome": "proximavis:cindel/jurassic_fields",
          "parameters": {
            "temperature": [
              -1.0,
              1.0
            ],
            "humidity": [
              -1.0,
              1.0
            ],
            "continentalness": 0.0,
            "erosion": [
              0.05,
              0.45
            ],
            "depth": 0.0,
            "weirdness": [
              0.05,
              0.267
            ],
            "offset": 0.0
          }
        },
        {
          "biome": "proximavis:cindel/carboniferous_swamp",
          "parameters": {
            "temperature": [
              -1.0,
              1.0
            ],
            "humidity": [
              -1.0,
              1.0
            ],
            "continentalness": 0.0,
            "erosion": [
              0.45,
              0.55
            ],
            "depth": 0.0,
            "weirdness": [
              0.05,
              0.267
            ],
            "offset": 0.0
          }
        },
        {
          "biome": "proximavis:cindel/carboniferous_swamp",
          "parameters": {
            "temperature": [
              -1.0,
              1.0
            ],
            "humidity": [
              -1.0,
              1.0
            ],
            "continentalness": 0.0,
            "erosion": [
              0.55,
              1.0
            ],
            "depth": 0.0,
            "weirdness": [
              0.05,
              0.267
            ],
            "offset": 0.0
          }
        },
        {
          "biome": "proximavis:cindel/jurassic_fields",
          "parameters": {
            "temperature": [
              -1.0,
              1.0
            ],
            "humidity": [
              -1.0,
              1.0
            ],
            "continentalness": 0.0,
            "erosion": [
              -1.0,
              -0.78
            ],
            "depth": 0.0,
            "weirdness": [
              -0.05,
              0.05
            ],
            "offset": 0.0
          }
        },
        {
          "biome": "proximavis:cindel/jurassic_fields",
          "parameters": {
            "temperature": [
              -1.0,
              1.0
            ],
            "humidity": [
              -1.0,
              1.0
            ],
            "continentalness": 0.0,
            "erosion": [
              -0.78,
              -0.375
            ],
            "depth": 0.0,
            "weirdness": [
              -0.05,
              0.05
            ],
            "offset": 0.0
          }
        },
        {
          "biome": "proximavis:cindel/river",
          "parameters": {
            "temperature": [
              -1.0,
              1.0
            ],
            "humidity": [
              -1.0,
              1.0
            ],
            "continentalness": 0.0,
            "erosion": [
              -0.375,
              -0.223
            ],
            "depth": 0.0,
            "weirdness": [
              -0.05,
              0.05
            ],
            "offset": 0.0
          }
        },
        {
          "biome": "proximavis:cindel/river",
          "parameters": {
            "temperature": [
              -1.0,
              1.0
            ],
            "humidity": [
              -1.0,
              1.0
            ],
            "continentalness": 0.0,
            "erosion": [
              -0.223,
              0.05
            ],
            "depth": 0.0,
            "weirdness": [
              -0.05,
              0.05
            ],
            "offset": 0.0
          }
        },
        {
          "biome": "proximavis:cindel/river",
          "parameters": {
            "temperature": [
              -1.0,
              1.0
            ],
            "humidity": [
              -1.0,
              1.0
            ],
            "continentalness": 0.0,
            "erosion": [
              0.05,
              0.45
            ],
            "depth": 0.0,
            "weirdness": [
              -0.05,
              0.05
            ],
            "offset": 0.0
          }
        },
        {
          "biome": "proximavis:cindel/carboniferous_swamp",
          "parameters": {
            "temperature": [
              -1.0,
              1.0
            ],
            "humidity": [
              -1.0,
              1.0
            ],
            "continentalness": 0.0,
            "erosion": [
              0.45,
              0.55
            ],
            "depth": 0.0,
            "weirdness": [
              -0.05,
              0.05
            ],
            "offset": 0.0
          }
        },
        {
          "biome": "proximavis:cindel/carboniferous_swamp",
          "parameters": {
            "temperature": [
              -1.0,
              1.0
            ],
            "humidity": [
              -1.0,
              1.0
            ],
            "continentalness": 0.0,
            "erosion": [
              0.55,
              1.0
            ],
            "depth": 0.0,
            "weirdness": [
              -0.05,
              0.05
            ],
            "offset": 0.0
          }
        },
        {
          "biome": "proximavis:cindel/jurassic_fields",
          "parameters": {
            "temperature": [
              -1.0,
              1.0
            ],
            "humidity": [
              -1.0,
              1.0
            ],
            "continentalness": 0.0,
            "erosion": [
              -1.0,
              -0.78
            ],
            "depth": 0.0,
            "weirdness": [
              -0.267,
              -0.05
            ],
            "offset": 0.0
          }
        },
        {
          "biome": "proximavis:cindel/jurassic_fields",
          "parameters": {
            "temperature": [
              -1.0,
              1.0
            ],
            "humidity": [
              -1.0,
              1.0
            ],
            "continentalness": 0.0,
            "erosion": [
              -0.78,
              -0.375
            ],
            "depth": 0.0,
            "weirdness": [
              -0.267,
              -0.05
            ],
            "offset": 0.0
          }
        },
        {
          "biome": "proximavis:cindel/jurassic_fields",
          "parameters": {
            "temperature": [
              -1.0,
              1.0
            ],
            "humidity": [
              -1.0,
              1.0
            ],
            "continentalness": 0.0,
            "erosion": [
              -0.375,
              -0.223
            ],
            "depth": 0.0,
            "weirdness": [
              -0.267,
              -0.05
            ],
            "offset": 0.0
          }
        },
        {
          "biome": "proximavis:cindel/jurassic_fields",
          "parameters": {
            "temperature": [
              -1.0,
              1.0
            ],
            "humidity": [
              -1.0,
              1.0
            ],
            "continentalness": 0.0,
            "erosion": [
              -0.223,
              0.05
            ],
            "depth": 0.0,
            "weirdness": [
              -0.267,
              -0.05
            ],
            "offset": 0.0
          }
        },
        {
          "biome": "proximavis:cindel/jurassic_fields",
          "parameters": {
            "temperature": [
              -1.0,
              1.0
            ],
            "humidity": [
              -1.0,
              1.0
            ],
            "continentalness": 0.0,
            "erosion": [
              0.05,
              0.45
            ],
            "depth": 0.0,
            "weirdness": [
              -0.267,
              -0.05
            ],
            "offset": 0.0
          }
        },
        {
          "biome": "proximavis:cindel/carboniferous_swamp",
          "parameters": {
            "temperature": [
              -1.0,
              1.0
            ],
            "humidity": [
              -1.0,
              1.0
            ],
            "continentalness": 0.0,
            "erosion": [
              0.45,
              0.55
            ],
            "depth": 0.0,
            "weirdness": [
              -0.267,
              -0.05
            ],
            "offset": 0.0
          }
        },
        {
          "biome": "proximavis:cindel/carboniferous_swamp",
          "parameters": {
            "temperature": [
              -1.0,
              1.0
            ],
            "humidity": [
              -1.0,
              1.0
            ],
            "continentalness": 0.0,
            "erosion": [
              0.55,
              1.0
            ],
            "depth": 0.0,
            "weirdness": [
              -0.267,
              -0.05
            ],
            "offset": 0.0
          }
        },
        {
          "biome": "proximavis:cindel/triassic_thicket",
          "parameters": {
            "temperature": [
              -1.0,
              1.0
            ],
            "humidity": [
              -1.0,
              1.0
            ],
            "continentalness": 0.0,
            "erosion": [
              -1.0,
              -0.78
            ],
            "depth": 0.0,
            "weirdness": [
              -0.4,
              -0.267
            ],
            "offset": 0.0
          }
        },
        {
          "biome": "proximavis:cindel/triassic_thicket",
          "parameters": {
            "temperature": [
              -1.0,
              1.0
            ],
            "humidity": [
              -1.0,
              1.0
            ],
            "continentalness": 0.0,
            "erosion": [
              -0.78,
              -0.375
            ],
            "depth": 0.0,
            "weirdness": [
              -0.4,
              -0.267
            ],
            "offset": 0.0
          }
        },
        {
          "biome": "proximavis:cindel/triassic_thicket",
          "parameters": {
            "temperature": [
              -1.0,
              1.0
            ],
            "humidity": [
              -1.0,
              1.0
            ],
            "continentalness": 0.0,
            "erosion": [
              -0.375,
              -0.223
            ],
            "depth": 0.0,
            "weirdness": [
              -0.4,
              -0.267
            ],
            "offset": 0.0
          }
        },
        {
          "biome": "proximavis:cindel/triassic_thicket",
          "parameters": {
            "temperature": [
              -1.0,
              1.0
            ],
            "humidity": [
              -1.0,
              1.0
            ],
            "continentalness": 0.0,
            "erosion": [
              -0.223,
              0.05
            ],
            "depth": 0.0,
            "weirdness": [
              -0.4,
              -0.267
            ],
            "offset": 0.0
          }
        },
        {
          "biome": "proximavis:cindel/triassic_thicket",
          "parameters": {
            "temperature": [
              -1.0,
              1.0
            ],
            "humidity": [
              -1.0,
              1.0
            ],
            "continentalness": 0.0,
            "erosion": [
              0.05,
              0.45
            ],
            "depth": 0.0,
            "weirdness": [
              -0.4,
              -0.267
            ],
            "offset": 0.0
          }
        },
        {
          "biome": "proximavis:cindel/triassic_thicket",
          "parameters": {
            "temperature": [
              -1.0,
              1.0
            ],
            "humidity": [
              -1.0,
              1.0
            ],
            "continentalness": 0.0,
            "erosion": [
              0.45,
              0.55
            ],
            "depth": 0.0,
            "weirdness": [
              -0.4,
              -0.267
            ],
            "offset": 0.0
          }
        },
        {
          "biome": "proximavis:cindel/carboniferous_swamp",
          "parameters": {
            "temperature": [
              -1.0,
              1.0
            ],
            "humidity": [
              -1.0,
              1.0
            ],
            "continentalness": 0.0,
            "erosion": [
              0.55,
              1.0
            ],
            "depth": 0.0,
            "weirdness": [
              -0.4,
              -0.267
            ],
            "offset": 0.0
          }
        },
        {
          "biome": "proximavis:cindel/triassic_thicket",
          "parameters": {
            "temperature": [
              -1.0,
              1.0
            ],
            "humidity": [
              -1.0,
              1.0
            ],
            "continentalness": 0.0,
            "erosion": [
              -1.0,
              -0.78
            ],
            "depth": 0.0,
            "weirdness": [
              -0.567,
              -0.4
            ],
            "offset": 0.0
          }
        },
        {
          "biome": "proximavis:cindel/triassic_thicket",
          "parameters": {
            "temperature": [
              -1.0,
              1.0
            ],
            "humidity": [
              -1.0,
              1.0
            ],
            "continentalness": 0.0,
            "erosion": [
              -0.78,
              -0.375
            ],
            "depth": 0.0,
            "weirdness": [
              -0.567,
              -0.4
            ],
            "offset": 0.0
          }
        },
        {
          "biome": "proximavis:cindel/triassic_thicket",
          "parameters": {
            "temperature": [
              -1.0,
              1.0
            ],
            "humidity": [
              -1.0,
              1.0
            ],
            "continentalness": 0.0,
            "erosion": [
              -0.375,
              -0.223
            ],
            "depth": 0.0,
            "weirdness": [
              -0.567,
              -0.4
            ],
            "offset": 0.0
          }
        },
        {
          "biome": "proximavis:cindel/triassic_thicket",
          "parameters": {
            "temperature": [
              -1.0,
              1.0
            ],
            "humidity": [
              -1.0,
              1.0
            ],
            "continentalness": 0.0,
            "erosion": [
              -0.223,
              0.05
            ],
            "depth": 0.0,
            "weirdness": [
              -0.567,
              -0.4
            ],
            "offset": 0.0
          }
        },
        {
          "biome": "proximavis:cindel/triassic_thicket",
          "parameters": {
            "temperature": [
              -1.0,
              1.0
            ],
            "humidity": [
              -1.0,
              1.0
            ],
            "continentalness": 0.0,
            "erosion": [
              0.05,
              0.45
            ],
            "depth": 0.0,
            "weirdness": [
              -0.567,
              -0.4
            ],
            "offset": 0.0
          }
        },
        {
          "biome": "proximavis:cindel/triassic_thicket",
          "parameters": {
            "temperature": [
              -1.0,
              1.0
            ],
            "humidity": [
              -1.0,
              1.0
            ],
            "continentalness": 0.0,
            "erosion": [
              0.45,
              0.55
            ],
            "depth": 0.0,
            "weirdness": [
              -0.567,
              -0.4
            ],
            "offset": 0.0
          }
        },
        {
          "biome": "proximavis:cindel/jurassic_fields",
          "parameters": {
            "temperature": [
              -1.0,
              1.0
            ],
            "humidity": [
              -1.0,
              1.0
            ],
            "continentalness": 0.0,
            "erosion": [
              0.55,
              1.0
            ],
            "depth": 0.0,
            "weirdness": [
              -0.567,
              -0.4
            ],
            "offset": 0.0
          }
        },
        {
          "biome": "proximavis:cindel/cretaceous_copse",
          "parameters": {
            "temperature": [
              -1.0,
              1.0
            ],
            "humidity": [
              -1.0,
              1.0
            ],
            "continentalness": 0.0,
            "erosion": [
              -1.0,
              -0.78
            ],
            "depth": 0.0,
            "weirdness": [
              -0.676,
              -0.567
            ],
            "offset": 0.0
          }
        },
        {
          "biome": "proximavis:cindel/cretaceous_copse",
          "parameters": {
            "temperature": [
              -1.0,
              1.0
            ],
            "humidity": [
              -1.0,
              1.0
            ],
            "continentalness": 0.0,
            "erosion": [
              -0.78,
              -0.375
            ],
            "depth": 0.0,
            "weirdness": [
              -0.676,
              -0.567
            ],
            "offset": 0.0
          }
        },
        {
          "biome": "proximavis:cindel/cretaceous_copse",
          "parameters": {
            "temperature": [
              -1.0,
              1.0
            ],
            "humidity": [
              -1.0,
              1.0
            ],
            "continentalness": 0.0,
            "erosion": [
              -0.375,
              -0.223
            ],
            "depth": 0.0,
            "weirdness": [
              -0.676,
              -0.567
            ],
            "offset": 0.0
          }
        },
        {
          "biome": "proximavis:cindel/cretaceous_copse",
          "parameters": {
            "temperature": [
              -1.0,
              1.0
            ],
            "humidity": [
              -1.0,
              1.0
            ],
            "continentalness": 0.0,
            "erosion": [
              -0.223,
              0.05
            ],
            "depth": 0.0,
            "weirdness": [
              -0.676,
              -0.567
            ],
            "offset": 0.0
          }
        },
        {
          "biome": "proximavis:cindel/cretaceous_copse",
          "parameters": {
            "temperature": [
              -1.0,
              1.0
            ],
            "humidity": [
              -1.0,
              1.0
            ],
            "continentalness": 0.0,
            "erosion": [
              0.05,
              0.45
            ],
            "depth": 0.0,
            "weirdness": [
              -0.676,
              -0.567
            ],
            "offset": 0.0
          }
        },
        {
          "biome": "proximavis:cindel/cretaceous_copse",
          "parameters": {
            "temperature": [
              -1.0,
              1.0
            ],
            "humidity": [
              -1.0,
              1.0
            ],
            "continentalness": 0.0,
            "erosion": [
              0.45,
              0.55
            ],
            "depth": 0.0,
            "weirdness": [
              -0.676,
              -0.567
            ],
            "offset": 0.0
          }
        },
        {
          "biome": "proximavis:cindel/jurassic_fields",
          "parameters": {
            "temperature": [
              -1.0,
              1.0
            ],
            "humidity": [
              -1.0,
              1.0
            ],
            "continentalness": 0.0,
            "erosion": [
              0.55,
              1.0
            ],
            "depth": 0.0,
            "weirdness": [
              -0.676,
              -0.567
            ],
            "offset": 0.0
          }
        },
        {
          "biome": "proximavis:cindel/cretaceous_copse",
          "parameters": {
            "temperature": [
              -1.0,
              1.0
            ],
            "humidity": [
              -1.0,
              1.0
            ],
            "continentalness": 0.0,
            "erosion": [
              -1.0,
              -0.78
            ],
            "depth": 0.0,
            "weirdness": [
              -0.933,
              -0.767
            ],
            "offset": 0.0
          }
        },
        {
          "biome": "proximavis:cindel/cretaceous_copse",
          "parameters": {
            "temperature": [
              -1.0,
              1.0
            ],
            "humidity": [
              -1.0,
              1.0
            ],
            "continentalness": 0.0,
            "erosion": [
              -0.78,
              -0.375
            ],
            "depth": 0.0,
            "weirdness": [
              -0.933,
              -0.767
            ],
            "offset": 0.0
          }
        },
        {
          "biome": "proximavis:cindel/cretaceous_copse",
          "parameters": {
            "temperature": [
              -1.0,
              1.0
            ],
            "humidity": [
              -1.0,
              1.0
            ],
            "continentalness": 0.0,
            "erosion": [
              -0.375,
              -0.223
            ],
            "depth": 0.0,
            "weirdness": [
              -0.933,
              -0.767
            ],
            "offset": 0.0
          }
        },
        {
          "biome": "proximavis:cindel/cretaceous_copse",
          "parameters": {
            "temperature": [
              -1.0,
              1.0
            ],
            "humidity": [
              -1.0,
              1.0
            ],
            "continentalness": 0.0,
            "erosion": [
              -0.223,
              0.05
            ],
            "depth": 0.0,
            "weirdness": [
              -0.933,
              -0.767
            ],
            "offset": 0.0
          }
        },
        {
          "biome": "proximavis:cindel/cretaceous_copse",
          "parameters": {
            "temperature": [
              -1.0,
              1.0
            ],
            "humidity": [
              -1.0,
              1.0
            ],
            "continentalness": 0.0,
            "erosion": [
              0.05,
              0.45
            ],
            "depth": 0.0,
            "weirdness": [
              -0.933,
              -0.767
            ],
            "offset": 0.0
          }
        },
        {
          "biome": "proximavis:cindel/cretaceous_copse",
          "parameters": {
            "temperature": [
              -1.0,
              1.0
            ],
            "humidity": [
              -1.0,
              1.0
            ],
            "continentalness": 0.0,
            "erosion": [
              0.45,
              0.55
            ],
            "depth": 0.0,
            "weirdness": [
              -0.933,
              -0.767
            ],
            "offset": 0.0
          }
        },
        {
          "biome": "proximavis:cindel/jurassic_fields",
          "parameters": {
            "temperature": [
              -1.0,
              1.0
            ],
            "humidity": [
              -1.0,
              1.0
            ],
            "continentalness": 0.0,
            "erosion": [
              0.55,
              1.0
            ],
            "depth": 0.0,
            "weirdness": [
              -0.933,
              -0.767
            ],
            "offset": 0.0
          }
        },
        {
          "biome": "proximavis:cindel/cretaceous_copse",
          "parameters": {
            "temperature": [
              -1.0,
              1.0
            ],
            "humidity": [
              -1.0,
              1.0
            ],
            "continentalness": 0.0,
            "erosion": [
              -1.0,
              -0.78
            ],
            "depth": 0.0,
            "weirdness": [
              -1.0,
              -0.933
            ],
            "offset": 0.0
          }
        },
        {
          "biome": "proximavis:cindel/cretaceous_copse",
          "parameters": {
            "temperature": [
              -1.0,
              1.0
            ],
            "humidity": [
              -1.0,
              1.0
            ],
            "continentalness": 0.0,
            "erosion": [
              -0.78,
              -0.375
            ],
            "depth": 0.0,
            "weirdness": [
              -1.0,
              -0.933
            ],
            "offset": 0.0
          }
        },
        {
          "biome": "proximavis:cindel/cretaceous_copse",
          "parameters": {
            "temperature": [
              -1.0,
              1.0
            ],
            "humidity": [
              -1.0,
              1.0
            ],
            "continentalness": 0.0,
            "erosion": [
              -0.375,
              -0.223
            ],
            "depth": 0.0,
            "weirdness": [
              -1.0,
              -0.933
            ],
            "offset": 0.0
          }
        },
        {
          "biome": "proximavis:cindel/cretaceous_copse",
          "parameters": {
            "temperature": [
              -1.0,
              1.0
            ],
            "humidity": [
              -1.0,
              1.0
            ],
            "continentalness": 0.0,
            "erosion": [
              -0.223,
              0.05
            ],
            "depth": 0.0,
            "weirdness": [
              -1.0,
              -0.933
            ],
            "offset": 0.0
          }
        },
        {
          "biome": "proximavis:cindel/cretaceous_copse",
          "parameters": {
            "temperature": [
              -1.0,
              1.0
            ],
            "humidity": [
              -1.0,
              1.0
            ],
            "continentalness": 0.0,
            "erosion": [
              0.05,
              0.45
            ],
            "depth": 0.0,
            "weirdness": [
              -1.0,
              -0.933
            ],
            "offset": 0.0
          }
        },
        {
          "biome": "proximavis:cindel/cretaceous_copse",
          "parameters": {
            "temperature": [
              -1.0,
              1.0
            ],
            "humidity": [
              -1.0,
              1.0
            ],
            "continentalness": 0.0,
            "erosion": [
              0.45,
              0.55
            ],
            "depth": 0.0,
            "weirdness": [
              -1.0,
              -0.933
            ],
            "offset": 0.0
          }
        },
        {
          "biome": "proximavis:cindel/carboniferous_swamp",
          "parameters": {
            "temperature": [
              -1.0,
              1.0
            ],
            "humidity": [
              -1.0,
              1.0
            ],
            "continentalness": 0.0,
            "erosion": [
              0.55,
              1.0
            ],
            "depth": 0.0,
            "weirdness": [
              -1.0,
              -0.933
            ],
            "offset": 0.0
          }
        }
      ]
    }
  }
}